ddsql/__init__.py
ddsql/adapter.py
ddsql/py.typed
ddsql/query.py
ddsql/serializers/__init__.py
ddsql/serializers/base.py
ddsql/serializers/clickhouse.py
ddsql/serializers/postgres.py
ddsql/sqlbase.py
ddsql-0.0.1.dist-info/METADATA
ddsql-0.0.1.dist-info/WHEEL
ddsql-0.0.1.dist-info/licenses/LICENSE
ddsql-0.0.1.dist-info/RECORD
