Metadata-Version: 2.4
Name: ddsql
Version: 0.0.1
Summary: SQL Query Library
License: MIT
License-File: LICENSE
Keywords: python,ddsql
Author: davyddd
Requires-Python: >=3.9,<3.15
Classifier: License :: OSI Approved :: MIT License
Classifier: Programming Language :: Python :: 3
Classifier: Programming Language :: Python :: 3.9
Classifier: Programming Language :: Python :: 3.10
Classifier: Programming Language :: Python :: 3.11
Classifier: Programming Language :: Python :: 3.12
Classifier: Programming Language :: Python :: 3.13
Classifier: Programming Language :: Python :: 3.14
Requires-Dist: ddutils (<0.2.0)
Requires-Dist: jinja2 (>=3.0.0,<4.0.0)
Project-URL: Repository, https://github.com/davyddd/ddsql
